{
    "title": "",
    "description": "",
    "parentClass": "\\MembersBundle\\Adapter\\Group\\AbstractGroup",
    "implementsInterfaces": "",
    "listingParentClass": "",
    "useTraits": "",
    "listingUseTraits": "",
    "allowInherit": false,
    "allowVariants": false,
    "showVariants": false,
    "layoutDefinitions": {
        "name": "pimcore_root",
        "type": null,
        "region": null,
        "title": null,
        "width": 0,
        "height": 0,
        "collapsible": false,
        "collapsed": false,
        "bodyStyle": null,
        "datatype": "layout",
        "children": [
            {
                "name": "Layout",
                "type": null,
                "region": null,
                "title": null,
                "width": 0,
                "height": 0,
                "collapsible": false,
                "collapsed": false,
                "bodyStyle": null,
                "datatype": "layout",
                "children": [
                    {
                        "name": "name",
                        "title": "Group Name",
                        "tooltip": "",
                        "mandatory": false,
                        "noteditable": false,
                        "index": 0,
                        "locked": false,
                        "style": "",
                        "permissions": null,
                        "fieldtype": "input",
                        "relationType": false,
                        "invisible": false,
                        "visibleGridView": false,
                        "visibleSearch": false,
                        "defaultValue": null,
                        "columnLength": 190,
                        "regex": "",
                        "regexFlags": [],
                        "unique": false,
                        "showCharCount": false,
                        "width": null,
                        "defaultValueGenerator": "",
                        "datatype": "data"
                    },
                    {
                        "name": "roles",
                        "title": "roles",
                        "tooltip": "",
                        "mandatory": false,
                        "noteditable": false,
                        "index": 0,
                        "locked": false,
                        "style": "",
                        "permissions": null,
                        "fieldtype": "multiselect",
                        "relationType": false,
                        "invisible": false,
                        "visibleGridView": false,
                        "visibleSearch": false,
                        "options": null,
                        "maxItems": null,
                        "renderType": null,
                        "optionsProviderClass": "@MembersBundle\\CoreExtension\\Provider\\RoleOptionsProvider",
                        "optionsProviderData": "",
                        "dynamicOptions": true,
                        "height": "",
                        "width": "",
                        "datatype": "data"
                    }
                ],
                "locked": false,
                "fieldtype": "panel",
                "layout": null,
                "border": false,
                "icon": null,
                "labelWidth": 100,
                "labelAlign": "left"
            }
        ],
        "locked": false,
        "fieldtype": "panel",
        "layout": null,
        "border": false,
        "icon": null,
        "labelWidth": 100,
        "labelAlign": "left"
    },
    "icon": "\/bundles\/members\/img\/objectGroup.svg",
    "group": "",
    "showAppLoggerTab": false,
    "linkGeneratorReference": "",
    "previewGeneratorReference": "",
    "compositeIndices": [],
    "showFieldLookup": false,
    "propertyVisibility": {
        "grid": {
            "id": true,
            "path": true,
            "published": true,
            "modificationDate": true,
            "creationDate": true
        },
        "search": {
            "id": true,
            "path": true,
            "published": true,
            "modificationDate": true,
            "creationDate": true
        }
    },
    "enableGridLocking": false
}